{
  "concours": "CCMP",
  "filiere": "MP",
  "date": "2016",
  "file": "CCMP_MP_2016.json",
  "status": 200,
  "time_s": 714.38,
  "data": {
    "parties": [
      {
        "titre_partie": "Présentation générale du système MC²E",
        "questions": [
          {
            "numero": "Q1",
            "mots_cles": [
              {
                "theme": "Cinématique : Fermeture géométrique",
                "semestre": "S1"
              }
            ]
          }
        ],
        "themes_partie": [
          "Cinématique"
        ]
      },
      {
        "titre_partie": "Validation des performances statiques des motorisations",
        "questions": [
          {
            "numero": "Q2",
            "mots_cles": [
              {
                "theme": "Statique : PFS",
                "semestre": "S2"
              }
            ]
          },
          {
            "numero": "Q3",
            "mots_cles": [
              {
                "theme": "Statique : PFS",
                "semestre": "S2"
              }
            ]
          },
          {
            "numero": "Q4",
            "mots_cles": [
              {
                "theme": "Statique : PFS",
                "semestre": "S2"
              }
            ]
          }
        ],
        "themes_partie": [
          "Statique"
        ]
      },
      {
        "titre_partie": "Analyse partielle de la structure de régulation en position des axes en rotation",
        "questions": [
          {
            "numero": "Q5",
            "mots_cles": [
              {
                "theme": "Asservissement : Schéma-blocs",
                "semestre": "S2"
              }
            ]
          },
          {
            "numero": "Q6",
            "mots_cles": [
              {
                "theme": "Asservissement : Précision",
                "semestre": "S2"
              }
            ]
          },
          {
            "numero": "Q7",
            "mots_cles": [
              {
                "theme": "Asservissement : Précision",
                "semestre": "S2"
              }
            ]
          }
        ],
        "themes_partie": [
          "Asservissement"
        ]
      },
      {
        "titre_partie": "Validation des performances de l'asservissement d'effort",
        "questions": [
          {
            "numero": "Q8",
            "mots_cles": [
              {
                "theme": "Cinématique : Lois entrée-sortie",
                "semestre": "S1"
              }
            ]
          },
          {
            "numero": "Q9",
            "mots_cles": [
              {
                "theme": "Énergétique : Inertie équivalente",
                "semestre": "S3"
              }
            ]
          },
          {
            "numero": "Q10",
            "mots_cles": [
              {
                "theme": "Énergétique : Puissance",
                "semestre": "S3"
              }
            ]
          },
          {
            "numero": "Q11",
            "mots_cles": [
              {
                "theme": "Énergétique : Théorème de l'Énergie Cinétique",
                "semestre": "S3"
              }
            ]
          }
        ],
        "themes_partie": [
          "Cinématique",
          "Énergétique"
        ]
      },
      {
        "titre_partie": "Modèle de connaissance de l'asservissement",
        "questions": [
          {
            "numero": "Q12",
            "mots_cles": [
              {
                "theme": "Asservissement : Schéma-blocs",
                "semestre": "S2"
              }
            ]
          },
          {
            "numero": "Q13",
            "mots_cles": [
              {
                "theme": "Asservissement : Fonction de transfert",
                "semestre": "S2"
              }
            ]
          },
          {
            "numero": "Q14",
            "mots_cles": [
              {
                "theme": "Asservissement : Fonction de transfert",
                "semestre": "S2"
              }
            ]
          },
          {
            "numero": "Q15",
            "mots_cles": [
              {
                "theme": "Asservissement : Fonction de transfert",
                "semestre": "S2"
              }
            ]
          },
          {
            "numero": "Q16",
            "mots_cles": [
              {
                "theme": "Asservissement : Fonction de transfert",
                "semestre": "S2"
              }
            ]
          }
        ],
        "themes_partie": [
          "Asservissement"
        ]
      },
      {
        "titre_partie": "Etude des performances en régulation d'effort lors de l'opération",
        "questions": [
          {
            "numero": "Q17",
            "mots_cles": [
              {
                "theme": "Asservissement : Précision",
                "semestre": "S2"
              }
            ]
          },
          {
            "numero": "Q18",
            "mots_cles": [
              {
                "theme": "Asservissement : Correcteur Proportionnel et intégral",
                "semestre": "S2"
              }
            ]
          },
          {
            "numero": "Q19",
            "mots_cles": [
              {
                "theme": "Asservissement : Stabilité",
                "semestre": "S2"
              }
            ]
          },
          {
            "numero": "Q20",
            "mots_cles": [
              {
                "theme": "Asservissement : Précision",
                "semestre": "S2"
              }
            ]
          },
          {
            "numero": "Q21",
            "mots_cles": [
              {
                "theme": "Asservissement : Précision",
                "semestre": "S2"
              }
            ]
          },
          {
            "numero": "Q22",
            "mots_cles": [
              {
                "theme": "Asservissement : Précision",
                "semestre": "S2"
              }
            ]
          }
        ],
        "themes_partie": [
          "Asservissement"
        ]
      }
    ],
    "ajouts": []
  }
}